awoxmeshlight/__init__.py
awoxmeshlight/packetutils.py
awoxmeshlight-0.2.0.dist-info/LICENSE
awoxmeshlight-0.2.0.dist-info/METADATA
awoxmeshlight-0.2.0.dist-info/WHEEL
awoxmeshlight-0.2.0.dist-info/top_level.txt
awoxmeshlight-0.2.0.dist-info/RECORD
