Metadata-Version: 2.1
Name: awoxmeshlight
Version: 0.2.0
Summary: A package to control Awox Mesh light bulbs.
Home-page: http://github.com/leiaz/python-awox-mesh-light
Author: Laetitia Berthelot
Author-email: leiaz@mailbox.org
License: MIT
Platform: UNKNOWN
Classifier: Development Status :: 3 - Alpha
Classifier: Intended Audience :: Developers
Classifier: License :: OSI Approved :: MIT License
Classifier: Programming Language :: Python :: 3
Classifier: Programming Language :: Python :: 2.7
Requires-Dist: bluepy
Requires-Dist: pycryptodome
